{
    "$schema": "https://schema.management.azure.com/schemas/2019-04-01/deploymentTemplate.json#",
    "contentVersion": "1.0.0.0",
    "parameters": {
        "workspace": {
            "type": "String"
        }
    },
    "resources": [
        {
            "id": "[concat(resourceId('Microsoft.OperationalInsights/workspaces/providers', parameters('workspace'), 'Microsoft.SecurityInsights'),'/alertRules/00075bf9-8392-4de5-bae7-b2322234e032')]",
            "name": "[concat(parameters('workspace'),'/Microsoft.SecurityInsights/00075bf9-8392-4de5-bae7-b2322234e032')]",
            "type": "Microsoft.OperationalInsights/workspaces/providers/alertRules",
            "kind": "Scheduled",
            "apiVersion": "2021-10-01-preview",
            "properties": {
                "displayName": "New internet-exposed SSH endpoints",
                "description": "Looks for SSH endpoints that rarely are accessed from a public IP address, in comparison with their history of sign-ins from private IP addresses.",
                "severity": "Medium",
                "enabled": true,
                "query": "let avgthreshold = 0;\nlet probabilityLimit = 0.01;\nlet ssh_logins = Syslog\n| where Facility contains \"auth\" and ProcessName =~ \"sshd\"\n| where SyslogMessage has \"Accepted\"\n| extend SourceIP = extract(\"(([0-9]{1,3})\\\\.([0-9]{1,3})\\\\.([0-9]{1,3})\\\\.(([0-9]{1,3})))\",1,SyslogMessage) \n| where isnotempty(SourceIP)\n| extend result = ipv4_is_private(SourceIP);\nssh_logins \n| summarize privatecount=countif(result== true), publiccount=countif(result==false) by HostName, HostIP, bin(EventTime, 1d)\n| summarize \npublicIPLoginHistory  = make_list(pack('IPCount', publiccount,  'logon_time', EventTime)),\nprivateIPLoginHistory = make_list(pack('IPCount', privatecount, 'logon_time', EventTime)) by HostName, HostIP\n| mv-apply publicIPLoginHistory = publicIPLoginHistory on\n(\n    order by todatetime(publicIPLoginHistory['logon_time']) asc\n    | summarize publicIPLoginCountList=make_list(toint(publicIPLoginHistory['IPCount'])), publicAverage=avg(toint(publicIPLoginHistory['IPCount'])), publicStd=stdev(toint(publicIPLoginHistory['IPCount'])), maxPublicLoginCount=max(toint(publicIPLoginHistory['IPCount']))\n)\n| mv-apply privateIPLoginHistory = privateIPLoginHistory on\n(\n    order by todatetime(privateIPLoginHistory['logon_time']) asc\n    | summarize privateIPLoginCountList=make_list(toint(privateIPLoginHistory['IPCount'])), privateAverage=avg(toint(privateIPLoginHistory['IPCount'])), privateStd=stdev(toint(privateIPLoginHistory['IPCount']))\n)\n// Some logins from private IPs\n| where privateAverage > avgthreshold\n// There is a non-zero number of logins from public IPs\n| where publicAverage > avgthreshold\n// Approximate probability of seeing login from a public IP is < 1%\n| extend probabilityPublic = publicAverage / (privateAverage + publicAverage)\n| where probabilityPublic < probabilityLimit\n// Today has the highest number of logins from public IPs that we've seen in the last week\n| extend publicLoginCountToday = publicIPLoginCountList[-1]\n| where publicLoginCountToday >= maxPublicLoginCount\n| extend HostCustomEntity = HostName\n// Optionally retrieve the original raw data for those logins that we've identified as potentially suspect\n// | join kind=rightsemi (\n//   ssh_logins\n//  | where result == false\n//  ) on HostName",
                "queryFrequency": "P1D",
                "queryPeriod": "P7D",
                "triggerOperator": "GreaterThan",
                "triggerThreshold": 0,
                "suppressionDuration": "PT5H",
                "suppressionEnabled": false,
                "startTimeUtc": "2023-03-14T08:00:00.000Z",
                "tactics": [
                    "InitialAccess"
                ],
                "techniques": [
                    "T1078"
                ],
                "alertRuleTemplateName": "4915c713-ab38-432e-800b-8e2d46933de6",
                "incidentConfiguration": {
                    "createIncident": true,
                    "groupingConfiguration": {
                        "enabled": false,
                        "reopenClosedIncident": false,
                        "lookbackDuration": "PT5H",
                        "matchingMethod": "AllEntities",
                        "groupByEntities": [],
                        "groupByAlertDetails": [],
                        "groupByCustomDetails": []
                    }
                },
                "eventGroupingSettings": {
                    "aggregationKind": "SingleAlert"
                },
                "alertDetailsOverride": null,
                "customDetails": null,
                "entityMappings": [
                    {
                        "entityType": "Host",
                        "fieldMappings": [
                            {
                                "identifier": "FullName",
                                "columnName": "HostCustomEntity"
                            }
                        ]
                    }
                ],
                "sentinelEntitiesMappings": null,
                "templateVersion": "1.0.2"
            }
        }
    ]
}